[
    {
        "questionSpanish": "Relacionar.",
        "questionKichwa": "",
        "correctAnswer": "",
        "audioPath": "",
        "imagePath": "",
        "questionType": "matching",
        "optionList": ["Payka utka kallpan", "Payka mana utka kallpanchu","Kikinkuna allimanta purin","Kikinkuna mana purinchu"],
        "words": ["Ella corre rápido","Ella no corre rapido","Ustedes caminan despacio","Ustedes no caminan"],
        "correctOrder": []
    },
    {
        "questionSpanish": "Relacionar.",
        "questionKichwa": "",
        "correctAnswer": "",
        "audioPath": "",
        "imagePath": "",
        "questionType": "matching",
        "optionList": ["Rumika allimanta mikun", "Rumika utka mikun."],
        "words": ["Rumi come despacio","Rumi come rápido"],
        "correctOrder": []
    },
    [
        {"speaker": "Atik" ,
        "bot": "Imanalla Asiriri" ,
        "translation": "" ,
        "audio": "U6_L4_P1.mp3"},
        {"speaker": "Asiri" ,
        "bot": "Allimi kani. Kanka?" ,
        "translation": "" ,
        "audio": "U6_L4_P1_1.mp3"},
        {"speaker": "Atik" ,
        "bot": "Allimi. Kanka utka kallpan. Mayman?" ,
        "translation": "" ,
        "audio": "U6_L4_P1_2.mp3"},
        {"speaker": "Asiri" ,
        "bot": "Otavaloman kuchita hatunkapak. Kanka allimanta purin. Maymantatak shamunki?" ,
        "translation": "" ,
        "audio": "U6_L4_P1_3.mp3"},
        {"speaker": "Atik" ,
        "bot": "Wasimanta. Ñukanchikpa mamaka piñashkami kan." ,
        "translation": "" ,
        "audio": "U6_L4_P1_4.mp3"},
        {"speaker": "Asiri" ,
        "bot": "Ahtatayy. Rinimi. Ashtakashkaman." ,
        "translation": "" ,
        "audio": "U6_L4_P1_5.mp3"},
        {"speaker": "Atik" ,
        "bot": "Ashtakashkaman" ,
        "translation": "" ,
        "audio": "U6_L4_P1_6.mp3"}
    ],
    {
        "questionSpanish": "Seleccionar según el audio.",
        "questionKichwa": "Pitak allimanta purin",
        "correctAnswer": "Atik",
        "audioPath": "",
        "imagePath": "U6_L4_Q1.png",
        "questionType": "multiple_choice",
        "optionList": ["Asiriri", "Atik"],
        "words": [],
        "correctOrder": []
    },
    {
        "questionSpanish": "Seleccionar según el audio.",
        "questionKichwa": "Maymantatak Atikka shamun",
        "correctAnswer": "Wasimanta",
        "audioPath": "",
        "imagePath": "U6_L4_Q2.png",
        "questionType": "multiple_choice",
        "optionList": ["Otavalomanta", "Wasiman","Wasimanta"],
        "words": [],
        "correctOrder": []
    },
    {
        "questionSpanish": "Seleccionar según el audio.",
        "questionKichwa": "Asirika allimanta kallpanchu",
        "correctAnswer": "Mana",
        "audioPath": "",
        "imagePath": "U6_L4_Q3.png",
        "questionType": "multiple_choice",
        "optionList": ["Ari", "Mana"],
        "words": [],
        "correctOrder": []
    },
    {
        "questionSpanish": "Seleccionar según el audio.",
        "questionKichwa": "Maymantak Asiririka rin",
        "correctAnswer": "Otavaloman",
        "audioPath": "",
        "imagePath": "U6_L4_Q4.png",
        "questionType": "multiple_choice",
        "optionList": ["Otavaloman", "Otavalomanta","wasiman","wasimanta"],
        "words": [],
        "correctOrder": []
    }

]